setup.py
ioloop/__init__.py
ioloop/epoll.py
ioloop/kqueue.py
ioloop.egg-info/PKG-INFO
ioloop.egg-info/SOURCES.txt
ioloop.egg-info/dependency_links.txt
ioloop.egg-info/top_level.txt
ioloop.egg-info/zip-safe