Metadata-Version: 1.1
Name: ioloop
Version: 0.1a
Summary: Simple IOloop by epoll or kqueue
Home-page: https://github.com/mengzhuo/ioloop
Author: Meng Zhuo
Author-email: mengzhuo1203@gmail.com
License: MIT
Platform: any
Classifier: Environment :: Web Environment
Classifier: Intended Audience :: Developers
Classifier: License :: OSI Approved :: BSD License
Classifier: Operating System :: OS Independent
Classifier: Programming Language :: Python :: 2.7
Classifier: Programming Language :: Python :: 3.3
Classifier: Programming Language :: Python :: 3.4
Classifier: Topic :: Internet :: WWW/HTTP :: Dynamic Content
Classifier: Topic :: Software Development :: Libraries :: Python Modules
